mariadb/__init__.py
mariadb/_mariadb.cp314-win_amd64.pyd
mariadb/connectionpool.py
mariadb/connections.py
mariadb/cursors.py
mariadb/dbapi20.py
mariadb/field.py
mariadb/release_info.py
mariadb/constants/CAPABILITY.py
mariadb/constants/CLIENT.py
mariadb/constants/CURSOR.py
mariadb/constants/ERR.py
mariadb/constants/EXT_FIELD_TYPE.py
mariadb/constants/FIELD_FLAG.py
mariadb/constants/FIELD_TYPE.py
mariadb/constants/INDICATOR.py
mariadb/constants/INFO.py
mariadb/constants/STATUS.py
mariadb/constants/TPC_STATE.py
mariadb/constants/__init__.py
mariadb-1.1.14.dist-info/licenses/LICENSE
mariadb-1.1.14.dist-info/METADATA
mariadb-1.1.14.dist-info/WHEEL
mariadb-1.1.14.dist-info/top_level.txt
mariadb-1.1.14.dist-info/RECORD
